[{"id":"2429","nama":"Al Hidayah Tarbiyah Islamiyah","nspp":"510013110013","alamat":"Jalan Kalampaian Muara Labuh.","kyai":"","kab_kota":{"id":"1311","nama":"Solok Selatan"},"provinsi":{"id":"13","nama":"Sumatera Barat"}},{"id":"2430","nama":"PP. BUSTANUL HUDA","nspp":"510013110014","alamat":"LUBUK GADANG SANGIR KAB. SOLOK SELATAN.","kyai":"Syarkawi","kab_kota":{"id":"1311","nama":"Solok Selatan"},"provinsi":{"id":"13","nama":"Sumatera Barat"}},{"id":"2431","nama":"Darul Ulum","nspp":"510013110015","alamat":"Jln.Raya Muara Labuh - Padang Km.19 Sungai Kalu.","kyai":"H. Akmal Ahmad","kab_kota":{"id":"1311","nama":"Solok Selatan"},"provinsi":{"id":"13","nama":"Sumatera Barat"}},{"id":"2432","nama":"Bustanul Huda","nspp":"512013110002","alamat":"Jl. Raya Bagindo Tan Ameh.","kyai":"-","kab_kota":{"id":"1311","nama":"Solok Selatan"},"provinsi":{"id":"13","nama":"Sumatera Barat"}},{"id":"2433","nama":"Tarjun Najah","nspp":"512313110006","alamat":"Gaduang Nagari Lubuk Gadang Timur.","kyai":"","kab_kota":{"id":"1311","nama":"Solok Selatan"},"provinsi":{"id":"13","nama":"Sumatera Barat"}},{"id":"2434","nama":"Andalusia","nspp":"512313110007","alamat":"Batu Bajarang.","kyai":"As'ari","kab_kota":{"id":"1311","nama":"Solok Selatan"},"provinsi":{"id":"13","nama":"Sumatera Barat"}}]