[{"id":"27057","nama":"Babussalam Ddi Kassi","nspp":"510073040001","alamat":"Jl. Lanto Dg Pasewang No 213 Kassi 92351.","kyai":"H.RAHIM MUSTAFA, LC","kab_kota":{"id":"7304","nama":"Jeneponto"},"provinsi":{"id":"73","nama":"Sulawesi Selatan"}},{"id":"27058","nama":"Darul I`tisham Embo","nspp":"510373040002","alamat":"Embo Desa Turatea.","kyai":"DR. H. MUNAWIR KS, M. Ag","kab_kota":{"id":"7304","nama":"Jeneponto"},"provinsi":{"id":"73","nama":"Sulawesi Selatan"}},{"id":"27059","nama":"PONDOK PESANTREN NURUL AZISDDI  BAROBBO","nspp":"510073040003","alamat":"Jl. Pesantren No.9 Barobbo.","kyai":"Rustang Halik, S. Ag, MA","kab_kota":{"id":"7304","nama":"Jeneponto"},"provinsi":{"id":"73","nama":"Sulawesi Selatan"}},{"id":"27060","nama":"Al-Hikam Pitape","nspp":"510073040004","alamat":"Dusun Pitape Desa Bungungloe.","kyai":"Achmad Syafri","kab_kota":{"id":"7304","nama":"Jeneponto"},"provinsi":{"id":"73","nama":"Sulawesi Selatan"}},{"id":"27062","nama":"Madaniyah Gunung Silanu","nspp":"510073040005","alamat":"Jl. Patriot No.12 Tombo- Tombolo.","kyai":"AHMAD DAUD","kab_kota":{"id":"7304","nama":"Jeneponto"},"provinsi":{"id":"73","nama":"Sulawesi Selatan"}},{"id":"27063","nama":"An-Nuriyah","nspp":"510073040006","alamat":"Bontocini.","kyai":"KH. Ahmad Yahya, Lc. M.Pd","kab_kota":{"id":"7304","nama":"Jeneponto"},"provinsi":{"id":"73","nama":"Sulawesi Selatan"}},{"id":"27064","nama":"Pondok Pesantren Baitullah Paranga","nspp":"510073040007","alamat":"Jl. Pendidikan No. 1 Paranga Desa Lentu Kecamatan Bontoramba.","kyai":"NAWIR","kab_kota":{"id":"7304","nama":"Jeneponto"},"provinsi":{"id":"73","nama":"Sulawesi Selatan"}},{"id":"27065","nama":"Nahdlatul Ulum 2 Bonto Parang","nspp":"510073040008","alamat":"Bonto Parang Kelurahan Tolo Selatan.","kyai":"K.H.Abd. Hayyong","kab_kota":{"id":"7304","nama":"Jeneponto"},"provinsi":{"id":"73","nama":"Sulawesi Selatan"}},{"id":"27066","nama":"Rahmatullah","nspp":"510073040009","alamat":"Tompo Kelara  Kelurahan Tolo Utara.","kyai":"BAHARUDDIN, S. PdI","kab_kota":{"id":"7304","nama":"Jeneponto"},"provinsi":{"id":"73","nama":"Sulawesi Selatan"}},{"id":"27067","nama":"Al Fatah","nspp":"510073040010","alamat":"Passereang.","kyai":"Ust. Salamun","kab_kota":{"id":"7304","nama":"Jeneponto"},"provinsi":{"id":"73","nama":"Sulawesi Selatan"}},{"id":"27068","nama":"Aal-Falah Arungkeke","nspp":"510373040011","alamat":"Jln. Pendidikan No. 1 Tamanroya.","kyai":"MAHADI GASSING","kab_kota":{"id":"7304","nama":"Jeneponto"},"provinsi":{"id":"73","nama":"Sulawesi Selatan"}},{"id":"27069","nama":"Darul Ihsan Munte","nspp":"510073040012","alamat":"Munte Desa Mangepong.","kyai":"Drs. KH. KAMALUDDIN SUKKU","kab_kota":{"id":"7304","nama":"Jeneponto"},"provinsi":{"id":"73","nama":"Sulawesi Selatan"}},{"id":"27070","nama":"PP MANNILINGI","nspp":"510073040013","alamat":"Jl. Mannilingi Dg Jalling No. 45 Bulo-bulo.","kyai":"KM. Hasyim, S. PdI","kab_kota":{"id":"7304","nama":"Jeneponto"},"provinsi":{"id":"73","nama":"Sulawesi Selatan"}},{"id":"27071","nama":"PP BABURRAHMAN","nspp":"510073040014","alamat":"Jl. Pabeta Dg Nompo.","kyai":"UST. NURDIN","kab_kota":{"id":"7304","nama":"Jeneponto"},"provinsi":{"id":"73","nama":"Sulawesi Selatan"}},{"id":"27072","nama":"PONDOK PESANTREN DARUSSALAF JENEPONTO","nspp":"510373040015","alamat":"Jl. Abdul Mutholib Kelurahan Empoang Kecamatan Binamj.","kyai":"ASKARY","kab_kota":{"id":"7304","nama":"Jeneponto"},"provinsi":{"id":"73","nama":"Sulawesi Selatan"}},{"id":"27073","nama":"PONDOK PESANTREN HIDAYATULLAH JENEPONTO","nspp":"510373040016","alamat":"Dusun bulu-bulu Desa Pallantikang Kecamatan Bangkala.","kyai":"ARMIN, S. Hi","kab_kota":{"id":"7304","nama":"Jeneponto"},"provinsi":{"id":"73","nama":"Sulawesi Selatan"}},{"id":"27074","nama":"PP. ULUL ALBAAB JENEPONTO","nspp":"510073040017","alamat":"Jl. Poros Romanga-taba, komp.BTn Aprilia Recidence.","kyai":"sulfiadi","kab_kota":{"id":"7304","nama":"Jeneponto"},"provinsi":{"id":"73","nama":"Sulawesi Selatan"}},{"id":"27075","nama":"PP. BAHRUL ULUM TAROWANG","nspp":"510073040018","alamat":"Kampung Bendi Desa PAO, Kecamatan Tarowang, Kab. Jeneponto.","kyai":"","kab_kota":{"id":"7304","nama":"Jeneponto"},"provinsi":{"id":"73","nama":"Sulawesi Selatan"}}]