[{"id":"900","nama":"PPS Ibnu qasim","nspp":"512373150010","alamat":"Jl. Poros Ujung Lero, Dusun Sabamparu, Desa Tasiwalie Kec. Suppa Kab. Pinrang.","kyai":"","kab_kota":{"id":"7315","nama":"Pinrang"},"provinsi":{"id":"73","nama":"Sulawesi Selatan"}},{"id":"27207","nama":"Darul Arqam Muhammadiyah","nspp":"512073150001","alamat":"Jl. A. Wahid No.1 Punnia, Labumpung Desa Bunga 91271.","kyai":"","kab_kota":{"id":"7315","nama":"Pinrang"},"provinsi":{"id":"73","nama":"Sulawesi Selatan"}},{"id":"27208","nama":"Manahilil Ulum Addariyah Ddi Kaballangang","nspp":"512073150002","alamat":"Jl. Kampus, Poros Pinrang Polman Km.15  Rw/Rt 01/01 Dusun Batri Desa Kaballangang.","kyai":"Muhammad Rasyid Ridha Ambo Dalle","kab_kota":{"id":"7315","nama":"Pinrang"},"provinsi":{"id":"73","nama":"Sulawesi Selatan"}},{"id":"27210","nama":"Manbaul Ulum Addariyah Ddi Patobong","nspp":"512073150003","alamat":"Jl. Poros Pinrang-Langnga Km. 13 Desa Patobong.","kyai":"","kab_kota":{"id":"7315","nama":"Pinrang"},"provinsi":{"id":"73","nama":"Sulawesi Selatan"}},{"id":"27211","nama":"Darul Qur`An Attaqwa Jampue","nspp":"512073150005","alamat":"Jl. Poros Waetuoe No.199 Kessie. Kelurahan Lanrisang.","kyai":"H. HILMI ALI YAFIE","kab_kota":{"id":"7315","nama":"Pinrang"},"provinsi":{"id":"73","nama":"Sulawesi Selatan"}},{"id":"27212","nama":"Ittihadul Usrati Wal-Jamaah Lerang-Lerang","nspp":"512073150006","alamat":"Jl. Sungai Saddang. Kel.Benteng Sawitto. Lerang-Lerang.","kyai":"","kab_kota":{"id":"7315","nama":"Pinrang"},"provinsi":{"id":"73","nama":"Sulawesi Selatan"}},{"id":"27213","nama":"Mazra`Atul Akhirah Baramuli","nspp":"512073150007","alamat":"Jl. Pole Baramuli Km.3 Poros Pinrang Polman Palia Paleteang 91227.","kyai":"H. Lukmanul Hakim, Lc","kab_kota":{"id":"7315","nama":"Pinrang"},"provinsi":{"id":"73","nama":"Sulawesi Selatan"}},{"id":"27214","nama":"Darul `Ulum Ath- Thahiriyah Paladang","nspp":"512073150008","alamat":"Jl. Poros Barugae - Jampue Km 08 Paladang Desa Mallongilongi 91261.","kyai":"K.H. M. THAHIR SYARKAWI","kab_kota":{"id":"7315","nama":"Pinrang"},"provinsi":{"id":"73","nama":"Sulawesi Selatan"}},{"id":"27215","nama":"PP Tassbeh Baitul Quran","nspp":"512073150009","alamat":"Jl. Serigala Lr. Smp 5 Pinrang.","kyai":"sulaeman Milla","kab_kota":{"id":"7315","nama":"Pinrang"},"provinsi":{"id":"73","nama":"Sulawesi Selatan"}},{"id":"27216","nama":"PP Ittihadiyah Tanreassona","nspp":"512073150011","alamat":"Tanreassona Jl. Poros Jampue Km.4 Desa Padakkalawa Kecamatan Mattiro Bulu Kabupaten Pinrang.","kyai":"Dr. K.H.ABD. SALAM LATARABBI, Lc, ma","kab_kota":{"id":"7315","nama":"Pinrang"},"provinsi":{"id":"73","nama":"Sulawesi Selatan"}}]