[{"id":"920","nama":"ibnu mas'ud","nspp":"512376040014","alamat":"ling.kampung baru. kel. manding kecamatan polewali.","kyai":"Kiyai Marjan Aki Rayyan","kab_kota":{"id":"7604","nama":"Polewali Mandar"},"provinsi":{"id":"76","nama":"Sulawesi Barat"}},{"id":"921","nama":"Al Qur'an Jabal Nur","nspp":"512376040005","alamat":".","kyai":"","kab_kota":{"id":"7604","nama":"Polewali Mandar"},"provinsi":{"id":"76","nama":"Sulawesi Barat"}},{"id":"27442","nama":"Husnul Khatimah","nspp":"512376040002","alamat":"Jl. Madatte.","kyai":"H.Andi Fadly Yusuf Aco, Lc, M.Si","kab_kota":{"id":"7604","nama":"Polewali Mandar"},"provinsi":{"id":"76","nama":"Sulawesi Barat"}},{"id":"27443","nama":"Pondok Pesantren Al-Risalah Batetangnga","nspp":"512376040003","alamat":"Jl. Poros Permandian Biru Salusoang.","kyai":"Kyai Mudir, S.Pd.I.","kab_kota":{"id":"7604","nama":"Polewali Mandar"},"provinsi":{"id":"76","nama":"Sulawesi Barat"}},{"id":"27444","nama":"DDI AL IHSAN KANANG","nspp":"510076040003","alamat":"Jl. Poros Mangondang No. 35.","kyai":"LUKMAN","kab_kota":{"id":"7604","nama":"Polewali Mandar"},"provinsi":{"id":"76","nama":"Sulawesi Barat"}},{"id":"27445","nama":"Nuhiyah Pambusuang","nspp":"512376040004","alamat":"Jl.Trans Sulawesi Polman.","kyai":"K.H.BISRI","kab_kota":{"id":"7604","nama":"Polewali Mandar"},"provinsi":{"id":"76","nama":"Sulawesi Barat"}},{"id":"27446","nama":"Pondok Pesantren Modern Al-Ikhlash","nspp":"510076040005","alamat":"Jl. Poros Majene Km. 27 Lampoko.","kyai":"Syafruddin","kab_kota":{"id":"7604","nama":"Polewali Mandar"},"provinsi":{"id":"76","nama":"Sulawesi Barat"}},{"id":"27447","nama":"Syekh Hasan Yamani","nspp":"512376040006","alamat":"Jl. Parappe.","kyai":"Fakhri Tajuddin Mahdy, Lc. M. Ag","kab_kota":{"id":"7604","nama":"Polewali Mandar"},"provinsi":{"id":"76","nama":"Sulawesi Barat"}},{"id":"27448","nama":"AHLUL QUR`AN","nspp":"512376040007","alamat":"Lingkungan Batu Batu Kel. Darma, Kec. polewali.","kyai":"Ust. Mujahid","kab_kota":{"id":"7604","nama":"Polewali Mandar"},"provinsi":{"id":"76","nama":"Sulawesi Barat"}},{"id":"27449","nama":"Miftahul Jannah","nspp":"510076040008","alamat":"Jl.Poros Tutar Lombok.","kyai":"H BAHARANG","kab_kota":{"id":"7604","nama":"Polewali Mandar"},"provinsi":{"id":"76","nama":"Sulawesi Barat"}},{"id":"27450","nama":"Salafiyah Al Ihsan Kenje","nspp":"512376040010","alamat":"Jl. Elang No. 10 Kenje.","kyai":"K. Rahmat R.S.Pd.I","kab_kota":{"id":"7604","nama":"Polewali Mandar"},"provinsi":{"id":"76","nama":"Sulawesi Barat"}},{"id":"27451","nama":"Ulumul Qur'an Fatimah Azzahra","nspp":"512376040012","alamat":"Jl. Poros Majene Sabang Subik Kec. Balanipa Kab. Polewali Mandar.","kyai":"","kab_kota":{"id":"7604","nama":"Polewali Mandar"},"provinsi":{"id":"76","nama":"Sulawesi Barat"}},{"id":"27452","nama":"Pondok Pesantren salafiyah Parappe","nspp":"512376040013","alamat":"Jl. Masjid Syuhada 45 Desa parappe.","kyai":"","kab_kota":{"id":"7604","nama":"Polewali Mandar"},"provinsi":{"id":"76","nama":"Sulawesi Barat"}},{"id":"27453","nama":"Al-Balad Kamande","nspp":"510076040013","alamat":"Jl.Poros Tutar.","kyai":"suardi.","kab_kota":{"id":"7604","nama":"Polewali Mandar"},"provinsi":{"id":"76","nama":"Sulawesi Barat"}},{"id":"27454","nama":"PP Al Wasilah Lemo","nspp":"510076040014","alamat":"Jl. Dusun Lemo Desa Kuajang.","kyai":"Suardi","kab_kota":{"id":"7604","nama":"Polewali Mandar"},"provinsi":{"id":"76","nama":"Sulawesi Barat"}},{"id":"27455","nama":"Nahdlatul Ulum Sarampu","nspp":"510076040015","alamat":"Jl.Al-Ma?arif Sarampu.","kyai":"MUH. ARSYAD","kab_kota":{"id":"7604","nama":"Polewali Mandar"},"provinsi":{"id":"76","nama":"Sulawesi Barat"}},{"id":"27456","nama":"Al-Jariyah Matakali","nspp":"510076040017","alamat":"Jl. Poros Majene.","kyai":"Fajrin Syahrin","kab_kota":{"id":"7604","nama":"Polewali Mandar"},"provinsi":{"id":"76","nama":"Sulawesi Barat"}}]