[{"id":"923","nama":"PPS Abdullah Ibnu Abbas","nspp":"510076060012","alamat":"Jl. Pasar Ikan Topoyo.","kyai":"Muh. Anwar","kab_kota":{"id":"7606","nama":"Mamuju Tengah"},"provinsi":{"id":"76","nama":"Sulawesi Barat"}},{"id":"27470","nama":"Pondok Pesantren Awaluddin Kuo","nspp":"510076060001","alamat":"Jl. Santri No. 01 Dusun Mamuji.","kyai":"Erwin Haryandi","kab_kota":{"id":"7606","nama":"Mamuju Tengah"},"provinsi":{"id":"76","nama":"Sulawesi Barat"}},{"id":"27471","nama":"Miftahul Mardiyah Kuo","nspp":"510076060002","alamat":"Jl. Poros Kuo-Polo Jajar.","kyai":"ICHSANUL AMRI","kab_kota":{"id":"7606","nama":"Mamuju Tengah"},"provinsi":{"id":"76","nama":"Sulawesi Barat"}},{"id":"27472","nama":"Al-Ikhwan","nspp":"510076060003","alamat":"Jalan Pesantren Nomor 04 Topoyo, Desa Topoyo.","kyai":"Ir.H.Mursalin, S.Pd.I, M.Pd","kab_kota":{"id":"7606","nama":"Mamuju Tengah"},"provinsi":{"id":"76","nama":"Sulawesi Barat"}},{"id":"27473","nama":"Darul Istiqamah Topoyo","nspp":"510076060004","alamat":"Jl. Pesantren Topoyo.","kyai":"Muhamad Anis, S.Pd.I","kab_kota":{"id":"7606","nama":"Mamuju Tengah"},"provinsi":{"id":"76","nama":"Sulawesi Barat"}},{"id":"27474","nama":"Husnayain","nspp":"510076060005","alamat":"Jl. Persemaian Salule'bo.","kyai":"Isman Maulana","kab_kota":{"id":"7606","nama":"Mamuju Tengah"},"provinsi":{"id":"76","nama":"Sulawesi Barat"}},{"id":"27475","nama":"Al-Chaeriyah Barakkang","nspp":"510076060006","alamat":"Jl. Desa Barakkang.","kyai":"Irsan","kab_kota":{"id":"7606","nama":"Mamuju Tengah"},"provinsi":{"id":"76","nama":"Sulawesi Barat"}},{"id":"27476","nama":"MADINATUNNAJAH","nspp":"510076060007","alamat":"Jl. Trans Sulawesi Barat.","kyai":"Suandi","kab_kota":{"id":"7606","nama":"Mamuju Tengah"},"provinsi":{"id":"76","nama":"Sulawesi Barat"}},{"id":"27477","nama":"Baiturrahman","nspp":"510076060008","alamat":"Jl. DesaTobadak.","kyai":"","kab_kota":{"id":"7606","nama":"Mamuju Tengah"},"provinsi":{"id":"76","nama":"Sulawesi Barat"}},{"id":"27478","nama":"An Nahdhah","nspp":"510076060009","alamat":"Jl. Ki Hajar Dewantara.","kyai":"Hamzah Radhi","kab_kota":{"id":"7606","nama":"Mamuju Tengah"},"provinsi":{"id":"76","nama":"Sulawesi Barat"}},{"id":"27479","nama":"Al Biruni","nspp":"510076060010","alamat":"Dusun Mora Km. 6 Karossa.","kyai":"Baharuddin.S","kab_kota":{"id":"7606","nama":"Mamuju Tengah"},"provinsi":{"id":"76","nama":"Sulawesi Barat"}},{"id":"27480","nama":"Nurul Ilmi","nspp":"510076060011","alamat":"Dusun karondang Babana.","kyai":"Khairul Yani","kab_kota":{"id":"7606","nama":"Mamuju Tengah"},"provinsi":{"id":"76","nama":"Sulawesi Barat"}}]